{"charges":[{"charge":"BEING DUMB DUMB","law":"DUMBNESS","severity":"Misdemeanor","committedBy":"Leland Garcia","id":"ceac9924-90e9-498d-a0d5-ec78e31e268e"},{"charge":"SWAGGGGERERER","law":"SWAG","severity":"Felony","committedBy":"Leland Garcia","id":"22cdc049-b220-483e-9191-1fea042d5121"}],"people":[{"peopleType":"Suspect","ssn":"60415234","firstName":"Leland","middleName":"BIG","lastName":"Garcia","addressLineOne":"674 Florida Ave","addressLineTwo":"Tampa, FL 78451","race":"White","sex":"M","dob":"2001-02-25","height":"5'3\"","weight":"120","hair":"Brown","eye":"Brown","phoneNumber":"7809123141","email":"lelandgarcia@gmail.com","license":"78455123","state":"FL","howIdentify":"State ID","id":"e37cbcac-f09b-46dd-a8db-ff5164bf31dc"},{"peopleType":"Complainant","ssn":"123454312","firstName":"Roejandel","middleName":"L","lastName":"Martin","addressLineOne":"542 Circle Blvd","addressLineTwo":"San Fran, CA 78451","race":"Asian","sex":"M","dob":"1995-09-14","height":"6'0\"","weight":"230","hair":"Brown","eye":"Brown","phoneNumber":"7894566123","email":"rjmartin@yahoo.com","license":"L2134123","state":"CA","howIdentify":"State ID","id":"a2c13c71-c2d9-4bcb-b42f-d87d29119d64"},{"peopleType":"Witness","ssn":"123541234","firstName":"Jordan","middleName":"Jeffrey","lastName":"Roessle","addressLineOne":"6783 Alabama St","addressLineTwo":"San Diego, CA 92465","race":"White","sex":"M","dob":"1995-04-25","height":"5'9\"","weight":"240","hair":"Brown","eye":"Green","phoneNumber":"9095451550","email":"jordanroessle@gmail.com","license":"L78945123","state":"CA","howIdentify":"Verbal","id":"644b4780-27d6-4547-ba0c-3221655ef1f6"}],"officers":[{"officerName":"Johan IDK","officerId":"321","resource":["Audio","Video","Supp","Pics"],"id":"956a81eb-064c-4b86-9fcd-c3078f67996c"},{"officerName":"Cesar Estrada","officerId":"123","resource":["Audio","Supp"],"id":"ec3f16b4-3de7-4b43-a0cb-09f3ff9142cc"}],"officerReporting":"Jordan Roessle","ihsCase":"876-1234","occurredFrom":"2024-03-03T10:21","occurredTo":"2024-03-03T11:01","datetimeReported":"2024-03-03T12:03","locationLineOne":"626 James St","locationLineTwo": "San Diego, CA 92338","jurisdiction":"Park/Playground","probableCause":"Sed ut perspiciatis unde omnis iste natus error sit voluptatem accusantium doloremque laudantium, totam rem aperiam, eaque ipsa quae ab illo inventore veritatis et quasi architecto beatae vitae dicta sunt explicabo. Nemo enim ipsam voluptatem quia voluptas sit aspernatur aut odit aut fugit, sed quia consequuntur magni dolores eos qui ratione voluptatem sequi nesciunt. Neque porro quisquam est, qui dolorem ipsum quia dolor sit amet, consectetur, adipisci velit, sed quia non numquam eius modi tempora incidunt ut labore et dolore magnam aliquam quaerat voluptatem. Ut enim ad minima veniam, quis nostrum exercitationem ullam corporis suscipit laboriosam, nisi ut aliquid ex ea commodi consequatur? Quis autem vel eum iure reprehenderit qui in ea voluptate velit esse quam nihil molestiae consequatur, vel illum qui dolorem eum fugiat quo voluptas nulla pariatur?"}